syops/__init__.py
syops/engine.py
syops/flops_counter.py
syops/ops.py
syops/utils.py
syops-0.0.5.dist-info/LICENSE
syops-0.0.5.dist-info/METADATA
syops-0.0.5.dist-info/WHEEL
syops-0.0.5.dist-info/top_level.txt
syops-0.0.5.dist-info/zip-safe
syops-0.0.5.dist-info/RECORD
