Metadata-Version: 2.1
Name: syops
Version: 0.0.5
Summary: Synaptic OPerations (SyOPs) counter for spiking neural networks
Home-page: https://github.com/iCGY96/syops-counter
Author: Guangyao Chen
Author-email: gy.chen@gmail.com
License: MIT
Classifier: Programming Language :: Python :: 3
License-File: LICENSE
Requires-Dist: torch
Requires-Dist: spikingjelly
